README.md
setup.py
autoencoders/__init__.py
autoencoders.egg-info/PKG-INFO
autoencoders.egg-info/SOURCES.txt
autoencoders.egg-info/dependency_links.txt
autoencoders.egg-info/top_level.txt